{
  "_comment": "Name collections carousel on the homepage. Featured entries appear first, then random popular collectors fill to `count`. Descriptions auto-populate from description-boxes/collection.json when the `collector` key matches. Collections with no image (neither configured nor found in ES) are dropped. Optional `alt` overrides the default alt text (collector name) — set this where a configured `figure` depicts something more specific than the collection name.",

  "enabled": true,

  "title": "Explore our collections",
  "count": 25,

  "poolSize": 80,
  "_comment_poolSize": "How many top collectors to sample random picks from (after featured entries).",

  "minDocCount": 100,
  "_comment_minDocCount": "Minimum number of records a collection must have to appear as a random pick. Featured entries bypass this.",

  "excludeCollectors": [
    "Unknown",
    "Unknown collector",
    "collector, Unknown",
    "Collector, Unknown"
  ],

  "featured": [
    { "collector": "BBC Heritage Collection" },
    { "collector": "Daily Herald Archive", "figure": "/assets/img/home/collections/daily-herald-archive.jpg", "alt": "Press photograph from the Daily Herald Archive" },
    { "collector": "Monotype Corporation Collection" },
    { "collector": "Stephen Hawking\u2019s Office", "figure": "/assets/img/home/collections/stephen-hawkings-office.jpg", "alt": "Stephen Hawking\u2019s office with his desk, wheelchair and personal belongings" },
    { "collector": "The Worshipful Company of Clockmakers" }
  ],

  "cache": {
    "refreshPeriodHours": 4
  }
}
